tools/__init__.py
tools/_version.py
tools/data2yaml.py
tools/main.py
tools/py.typed
tools/utils.py
tools/excel2yaml/__init__.py
tools/excel2yaml/cli.py
tools/excel2yaml/dataset_metadata.py
tools/excel2yaml/dependent_variable.py
tools/excel2yaml/get_dataset_config.py
tools/excel2yaml/get_retriever_config.py
tools/excel2yaml/independent_variable.py
tools/excel2yaml/ruamel_styles.py
tools/excel2yaml/template.xlsx
tools/excel2yaml/time_variable.py
tools/excel2yaml/write_yaml.py
tsdat_tools-0.3.1.dist-info/METADATA
tsdat_tools-0.3.1.dist-info/WHEEL
tsdat_tools-0.3.1.dist-info/entry_points.txt
tsdat_tools-0.3.1.dist-info/top_level.txt
tsdat_tools-0.3.1.dist-info/RECORD
