Metadata-Version: 2.1
Name: tsdat-tools
Version: 0.3.1
Summary: Utility scripts and tools for tsdat.
Author-email: Maxwell Levin <24307537+maxwelllevin@users.noreply.github.com>, James McVey <53623232+jmcvey3@users.noreply.github.com>
License: BSD 3-Clause License
Keywords: tsdat,utils,config
Classifier: Programming Language :: Python :: 3
Requires-Python: >=3.10
Requires-Dist: tsdat>=0.7.0
Requires-Dist: pydantic<2.0.0
Requires-Dist: ruamel.yaml
Requires-Dist: typer
Requires-Dist: openpyxl
Requires-Dist: pandas
